{"metadata": {"dbt_schema_version": "https://schemas.getdbt.com/dbt/catalog/v1.json", "dbt_version": "0.21.1", "generated_at": "2022-10-05T16:55:49.114845Z", "invocation_id": "9ef309b9-7ca0-45a6-b87f-bdaf42b42cd6", "env": {}}, "nodes": {"model.emd.viagem_onibus": {"metadata": {"type": "table", "schema": "transporte_rodoviario_municipal", "name": "viagem_onibus", "database": "datario-dev", "comment": null, "owner": null}, "columns": {"data": {"type": "DATE", "index": 1, "name": "data", "comment": "Data de emiss\u00e3o do sinal de GPS"}, "consorcio": {"type": "STRING", "index": 2, "name": "consorcio", "comment": "Cons\u00f3rcio ao qual o servi\u00e7o pertence"}, "tipo_dia": {"type": "STRING", "index": 3, "name": "tipo_dia", "comment": "Dia da semana considerado para o c\u00e1lculo da dist\u00e2ncia planejada - categorias: Dia \u00datil, S\u00e1bado, Domingo"}, "id_empresa": {"type": "STRING", "index": 4, "name": "id_empresa", "comment": "C\u00f3digo identificador da empresa que opera o ve\u00edculo"}, "id_veiculo": {"type": "STRING", "index": 5, "name": "id_veiculo", "comment": "C\u00f3digo identificador do ve\u00edculo (n\u00famero de ordem)"}, "id_viagem": {"type": "STRING", "index": 6, "name": "id_viagem", "comment": "C\u00f3digo identificador da viagem (id_veiculo + servico + datetime_partida)"}, "servico": {"type": "STRING", "index": 7, "name": "servico", "comment": "Servi\u00e7o informado pelo GPS do ve\u00edculo"}, "shape_id": {"type": "STRING", "index": 8, "name": "shape_id", "comment": "C\u00f3digo identificador do shape (trajeto) do servi\u00e7o. O shape de servi\u00e7os Circurlares (C) \u00e9 quebrado no GTFS como Ida (I) e Volta (V) e tratado no algor\u00edtimo do subs\u00eddio para identifica\u00e7\u00e3o da viagem completa - veja o tratamento completo em https://github.com/prefeitura-rio/queries-rj-smtr/tree/master/models/projeto_subsidio_sppo"}, "sentido": {"type": "STRING", "index": 9, "name": "sentido", "comment": "Sentido do trajeto identificado - categorias: I (ida), V (volta), C (circular)"}, "datetime_partida": {"type": "DATETIME", "index": 10, "name": "datetime_partida", "comment": "Hor\u00e1rio de in\u00edcio da viagem"}, "datetime_chegada": {"type": "DATETIME", "index": 11, "name": "datetime_chegada", "comment": "Hor\u00e1rio de fim da viagem"}, "tempo_viagem": {"type": "INT64", "index": 12, "name": "tempo_viagem", "comment": "Tempo aferido da viagem (em minutos)"}, "distancia_planejada": {"type": "FLOAT64", "index": 13, "name": "distancia_planejada", "comment": "Dist\u00e2ncia do shape (trajeto) planejado"}, "perc_conformidade_shape": {"type": "FLOAT64", "index": 14, "name": "perc_conformidade_shape", "comment": "Percentual de sinais emitidos dentro do shape (trajeto) ao longo da viagem"}, "perc_conformidade_registros": {"type": "FLOAT64", "index": 15, "name": "perc_conformidade_registros", "comment": "Percentual de minutos da viagem com registro de sinal de GPS"}, "versao_modelo": {"type": "STRING", "index": 16, "name": "versao_modelo", "comment": "Vers\u00e3o da metodologia de c\u00e1lculo da respectiva linha na tabela."}}, "stats": {"num_rows": {"id": "num_rows", "label": "# Rows", "value": 3143470.0, "include": true, "description": "Approximate count of rows in this table"}, "num_bytes": {"id": "num_bytes", "label": "Approximate Size", "value": 489289450.0, "include": true, "description": "Approximate size of table as reported by BigQuery"}, "partitioning_type": {"id": "partitioning_type", "label": "Partitioned By", "value": "data", "include": true, "description": "The partitioning column for this table"}, "has_stats": {"id": "has_stats", "label": "Has Stats?", "value": true, "include": false, "description": "Indicates whether there are statistics for this table"}}, "unique_id": "model.emd.viagem_onibus"}}, "sources": {}, "errors": null}