{"metadata": {"dbt_schema_version": "https://schemas.getdbt.com/dbt/run-results/v3.json", "dbt_version": "0.21.1", "generated_at": "2022-06-08T17:51:41.096344Z", "invocation_id": "02976388-c590-4e62-a8e9-bb43d8cbf3c2", "env": {}}, "results": [{"status": "success", "timing": [{"name": "compile", "started_at": "2022-06-08T17:51:40.955212Z", "completed_at": "2022-06-08T17:51:40.963677Z"}, {"name": "execute", "started_at": "2022-06-08T17:51:40.964028Z", "completed_at": "2022-06-08T17:51:40.964059Z"}], "thread_id": "Thread-2", "execution_time": 0.010112285614013672, "adapter_response": {}, "message": null, "failures": null, "unique_id": "model.emd.aluno_historico"}, {"status": "success", "timing": [{"name": "compile", "started_at": "2022-06-08T17:51:40.954922Z", "completed_at": "2022-06-08T17:51:40.964769Z"}, {"name": "execute", "started_at": "2022-06-08T17:51:40.965409Z", "completed_at": "2022-06-08T17:51:40.965418Z"}], "thread_id": "Thread-1", "execution_time": 0.012543916702270508, "adapter_response": {}, "message": null, "failures": null, "unique_id": "model.emd.aluno"}, {"status": "success", "timing": [{"name": "compile", "started_at": "2022-06-08T17:51:40.966732Z", "completed_at": "2022-06-08T17:51:40.978358Z"}, {"name": "execute", "started_at": "2022-06-08T17:51:40.978986Z", "completed_at": "2022-06-08T17:51:40.978996Z"}], "thread_id": "Thread-2", "execution_time": 0.013957500457763672, "adapter_response": {}, "message": null, "failures": null, "unique_id": "model.emd.aluno_turma"}, {"status": "success", "timing": [{"name": "compile", "started_at": "2022-06-08T17:51:40.972691Z", "completed_at": "2022-06-08T17:51:40.978670Z"}, {"name": "execute", "started_at": "2022-06-08T17:51:40.979289Z", "completed_at": "2022-06-08T17:51:40.979299Z"}], "thread_id": "Thread-1", "execution_time": 0.007920503616333008, "adapter_response": {}, "message": null, "failures": null, "unique_id": "model.emd.avaliacao"}, {"status": "success", "timing": [{"name": "compile", "started_at": "2022-06-08T17:51:40.982189Z", "completed_at": "2022-06-08T17:51:40.987336Z"}, {"name": "execute", "started_at": "2022-06-08T17:51:40.987690Z", "completed_at": "2022-06-08T17:51:40.987699Z"}], "thread_id": "Thread-2", "execution_time": 0.007049083709716797, "adapter_response": {}, "message": null, "failures": null, "unique_id": "model.emd.bairro"}, {"status": "success", "timing": [{"name": "compile", "started_at": "2022-06-08T17:51:40.990078Z", "completed_at": "2022-06-08T17:51:40.996028Z"}, {"name": "execute", "started_at": "2022-06-08T17:51:40.996359Z", "completed_at": "2022-06-08T17:51:40.996367Z"}], "thread_id": "Thread-2", "execution_time": 0.007421255111694336, "adapter_response": {}, "message": null, "failures": null, "unique_id": "model.emd.coc"}, {"status": "success", "timing": [{"name": "compile", "started_at": "2022-06-08T17:51:40.982472Z", "completed_at": "2022-06-08T17:51:41.015651Z"}, {"name": "execute", "started_at": "2022-06-08T17:51:41.016002Z", "completed_at": "2022-06-08T17:51:41.016013Z"}], "thread_id": "Thread-1", "execution_time": 0.034697771072387695, "adapter_response": {}, "message": null, "failures": null, "unique_id": "model.emd.chamado"}, {"status": "success", "timing": [{"name": "compile", "started_at": "2022-06-08T17:51:41.003104Z", "completed_at": "2022-06-08T17:51:41.017128Z"}, {"name": "execute", "started_at": "2022-06-08T17:51:41.017856Z", "completed_at": "2022-06-08T17:51:41.017864Z"}], "thread_id": "Thread-2", "execution_time": 0.020551204681396484, "adapter_response": {}, "message": null, "failures": null, "unique_id": "model.emd.dependencia"}, {"status": "success", "timing": [{"name": "compile", "started_at": "2022-06-08T17:51:41.018145Z", "completed_at": "2022-06-08T17:51:41.021927Z"}, {"name": "execute", "started_at": "2022-06-08T17:51:41.023796Z", "completed_at": "2022-06-08T17:51:41.023807Z"}], "thread_id": "Thread-1", "execution_time": 0.0069658756256103516, "adapter_response": {}, "message": null, "failures": null, "unique_id": "model.emd.escola"}, {"status": "success", "timing": [{"name": "compile", "started_at": "2022-06-08T17:51:41.021687Z", "completed_at": "2022-06-08T17:51:41.025080Z"}, {"name": "execute", "started_at": "2022-06-08T17:51:41.025794Z", "completed_at": "2022-06-08T17:51:41.025802Z"}], "thread_id": "Thread-2", "execution_time": 0.005462646484375, "adapter_response": {}, "message": null, "failures": null, "unique_id": "model.emd.estacoes_alertario"}, {"status": "success", "timing": [{"name": "compile", "started_at": "2022-06-08T17:51:41.026077Z", "completed_at": "2022-06-08T17:51:41.029690Z"}, {"name": "execute", "started_at": "2022-06-08T17:51:41.035002Z", "completed_at": "2022-06-08T17:51:41.035013Z"}], "thread_id": "Thread-1", "execution_time": 0.010215044021606445, "adapter_response": {}, "message": null, "failures": null, "unique_id": "model.emd.estacoes_inmet"}, {"status": "success", "timing": [{"name": "compile", "started_at": "2022-06-08T17:51:41.029448Z", "completed_at": "2022-06-08T17:51:41.036235Z"}, {"name": "execute", "started_at": "2022-06-08T17:51:41.036963Z", "completed_at": "2022-06-08T17:51:41.036971Z"}], "thread_id": "Thread-2", "execution_time": 0.008679628372192383, "adapter_response": {}, "message": null, "failures": null, "unique_id": "model.emd.frequencia"}, {"status": "success", "timing": [{"name": "compile", "started_at": "2022-06-08T17:51:41.043941Z", "completed_at": "2022-06-08T17:51:41.049143Z"}, {"name": "execute", "started_at": "2022-06-08T17:51:41.049430Z", "completed_at": "2022-06-08T17:51:41.049437Z"}], "thread_id": "Thread-2", "execution_time": 0.0063190460205078125, "adapter_response": {}, "message": null, "failures": null, "unique_id": "model.emd.gps_onibus"}, {"status": "success", "timing": [{"name": "compile", "started_at": "2022-06-08T17:51:41.037250Z", "completed_at": "2022-06-08T17:51:41.050929Z"}, {"name": "execute", "started_at": "2022-06-08T17:51:41.051507Z", "completed_at": "2022-06-08T17:51:41.051515Z"}], "thread_id": "Thread-1", "execution_time": 0.017150163650512695, "adapter_response": {}, "message": null, "failures": null, "unique_id": "model.emd.gps_brt"}, {"status": "success", "timing": [{"name": "compile", "started_at": "2022-06-08T17:51:41.051231Z", "completed_at": "2022-06-08T17:51:41.054915Z"}, {"name": "execute", "started_at": "2022-06-08T17:51:41.055471Z", "completed_at": "2022-06-08T17:51:41.055479Z"}], "thread_id": "Thread-2", "execution_time": 0.010294198989868164, "adapter_response": {}, "message": null, "failures": null, "unique_id": "model.emd.logradouro"}, {"status": "success", "timing": [{"name": "compile", "started_at": "2022-06-08T17:51:41.055194Z", "completed_at": "2022-06-08T17:51:41.061990Z"}, {"name": "execute", "started_at": "2022-06-08T17:51:41.062584Z", "completed_at": "2022-06-08T17:51:41.062593Z"}], "thread_id": "Thread-1", "execution_time": 0.013530492782592773, "adapter_response": {}, "message": null, "failures": null, "unique_id": "model.emd.meteorologia_inmet"}, {"status": "success", "timing": [{"name": "compile", "started_at": "2022-06-08T17:51:41.062291Z", "completed_at": "2022-06-08T17:51:41.069515Z"}, {"name": "execute", "started_at": "2022-06-08T17:51:41.074566Z", "completed_at": "2022-06-08T17:51:41.074576Z"}], "thread_id": "Thread-2", "execution_time": 0.013507843017578125, "adapter_response": {}, "message": null, "failures": null, "unique_id": "model.emd.movimentacao"}, {"status": "success", "timing": [{"name": "compile", "started_at": "2022-06-08T17:51:41.069275Z", "completed_at": "2022-06-08T17:51:41.075772Z"}, {"name": "execute", "started_at": "2022-06-08T17:51:41.076503Z", "completed_at": "2022-06-08T17:51:41.076512Z"}], "thread_id": "Thread-1", "execution_time": 0.008394002914428711, "adapter_response": {}, "message": null, "failures": null, "unique_id": "model.emd.quantidade_agua_precipitavel_satelite"}, {"status": "success", "timing": [{"name": "compile", "started_at": "2022-06-08T17:51:41.076797Z", "completed_at": "2022-06-08T17:51:41.089167Z"}, {"name": "execute", "started_at": "2022-06-08T17:51:41.089497Z", "completed_at": "2022-06-08T17:51:41.089506Z"}], "thread_id": "Thread-2", "execution_time": 0.013842105865478516, "adapter_response": {}, "message": null, "failures": null, "unique_id": "model.emd.taxa_precipitacao_alertario"}, {"status": "success", "timing": [{"name": "compile", "started_at": "2022-06-08T17:51:41.084287Z", "completed_at": "2022-06-08T17:51:41.090166Z"}, {"name": "execute", "started_at": "2022-06-08T17:51:41.090855Z", "completed_at": "2022-06-08T17:51:41.090864Z"}], "thread_id": "Thread-1", "execution_time": 0.007890462875366211, "adapter_response": {}, "message": null, "failures": null, "unique_id": "model.emd.taxa_precipitacao_satelite"}, {"status": "success", "timing": [{"name": "compile", "started_at": "2022-06-08T17:51:41.092058Z", "completed_at": "2022-06-08T17:51:41.093929Z"}, {"name": "execute", "started_at": "2022-06-08T17:51:41.094187Z", "completed_at": "2022-06-08T17:51:41.094195Z"}], "thread_id": "Thread-2", "execution_time": 0.003441333770751953, "adapter_response": {}, "message": null, "failures": null, "unique_id": "model.emd.turma"}], "elapsed_time": 1.184264898300171, "args": {"log_format": "default", "write_json": true, "use_experimental_parser": false, "profiles_dir": "/home/runner/work/queries-datario/queries-datario", "use_cache": true, "compile": true, "version_check": true, "which": "generate", "rpc_method": "docs.generate"}}